brainways_reg_model/__init__.py
brainways_reg_model/_version.py
brainways_reg_model/brainways_reg_model.py
brainways_reg_model/cli/__init__.py
brainways_reg_model/cli/cli.py
brainways_reg_model/cli/prepare_annotation_data.py
brainways_reg_model/cli/prepare_real_data.py
brainways_reg_model/cli/prepare_synth_data.py
brainways_reg_model/cli/view_dataset.py
brainways_reg_model/model/__init__.py
brainways_reg_model/model/approx_acc.py
brainways_reg_model/model/atlas_registration_params.py
brainways_reg_model/model/dataset.py
brainways_reg_model/model/evaluate.py
brainways_reg_model/model/metric_dict_input_wrapper.py
brainways_reg_model/model/model.py
brainways_reg_model/model/predict.py
brainways_reg_model/model/predict_qupath.py
brainways_reg_model/model/registration_params.py
brainways_reg_model/model/train.py
brainways_reg_model/slice_generator/__init__.py
brainways_reg_model/slice_generator/slice_generator.py
brainways_reg_model/slice_generator/slice_generator_sample.py
brainways_reg_model/slice_generator/stages/__init__.py
brainways_reg_model/slice_generator/stages/adjust_contrast.py
brainways_reg_model/slice_generator/stages/crop_material_area.py
brainways_reg_model/slice_generator/stages/filter_regions.py
brainways_reg_model/slice_generator/stages/random_affine.py
brainways_reg_model/slice_generator/stages/random_elastic_deformation.py
brainways_reg_model/slice_generator/stages/random_light_deformation.py
brainways_reg_model/slice_generator/stages/random_lighten_dark_areas.py
brainways_reg_model/slice_generator/stages/random_mask_regions.py
brainways_reg_model/slice_generator/stages/random_single_hemisphere.py
brainways_reg_model/slice_generator/stages/random_zero_below_threshold.py
brainways_reg_model/slice_generator/stages/resize.py
brainways_reg_model/slice_generator/stages/to_kornia.py
brainways_reg_model/slice_generator/stages/to_pil_image.py
brainways_reg_model/utils/__init__.py
brainways_reg_model/utils/config.py
brainways_reg_model/utils/data.py
brainways_reg_model-0.1.dist-info/LICENSE
brainways_reg_model-0.1.dist-info/METADATA
brainways_reg_model-0.1.dist-info/WHEEL
brainways_reg_model-0.1.dist-info/entry_points.txt
brainways_reg_model-0.1.dist-info/top_level.txt
brainways_reg_model-0.1.dist-info/RECORD
