Metadata-Version: 2.1
Name: brainways-reg-model
Version: 0.1
Summary: Brainways Registration Model
Home-page: https://github.com/bkntr/brainways-reg-model
Author: Ben Kantor
Author-email: benkantor@mail.tau.ac.il
License: GPL-3.0
Project-URL: Bug Tracker, https://github.com/bkntr/brainways-reg-model/issues
Project-URL: Documentation, https://github.com/bkntr/brainways-reg-model#README.md
Project-URL: Source Code, https://github.com/bkntr/brainways-reg-model
Project-URL: User Support, https://github.com/bkntr/brainways-reg-model/issues
Platform: UNKNOWN
Classifier: Development Status :: 2 - Pre-Alpha
Classifier: Intended Audience :: Developers
Classifier: License :: OSI Approved :: GNU General Public License v3 (GPLv3)
Classifier: Operating System :: OS Independent
Classifier: Programming Language :: Python
Classifier: Programming Language :: Python :: 3
Classifier: Programming Language :: Python :: 3 :: Only
Classifier: Programming Language :: Python :: 3.6
Classifier: Programming Language :: Python :: 3.7
Classifier: Programming Language :: Python :: 3.8
Classifier: Programming Language :: Python :: 3.9
Classifier: Programming Language :: Python :: 3.10
Classifier: Programming Language :: Python :: Implementation :: CPython
Classifier: Topic :: Scientific/Engineering :: Image Processing
Requires-Python: >=3.6
License-File: LICENSE
Requires-Dist: bg-atlasapi
Requires-Dist: click
Requires-Dist: dacite
Requires-Dist: kornia (==0.6.7)
Requires-Dist: numpy
Requires-Dist: pytorch-lightning (==1.6.3)
Requires-Dist: setuptools (<=59.5.0)
Requires-Dist: torch (==1.10.*)
Requires-Dist: torchmetrics (==0.6.0)
Requires-Dist: torchvision (==0.11.*)
Provides-Extra: dev
Requires-Dist: pytest ; extra == 'dev'
Requires-Dist: tox ; extra == 'dev'
Requires-Dist: dvc ; extra == 'dev'
Requires-Dist: pre-commit ; extra == 'dev'
Provides-Extra: testing
Requires-Dist: pytest ; extra == 'testing'
Requires-Dist: tox ; extra == 'testing'
